gempaTerkini/__init__.py
indonesia_latestearthquake_Rx168059-2024.0.0.7.dist-info/LICENSE
indonesia_latestearthquake_Rx168059-2024.0.0.7.dist-info/METADATA
indonesia_latestearthquake_Rx168059-2024.0.0.7.dist-info/WHEEL
indonesia_latestearthquake_Rx168059-2024.0.0.7.dist-info/top_level.txt
indonesia_latestearthquake_Rx168059-2024.0.0.7.dist-info/RECORD
