Metadata-Version: 2.1
Name: indonesia-latestearthquake_Rx168059
Version: 2024.0.0.7
Summary: This package will get information about latest earthquake from BMKG(Indonesian Agency for Meteorological, Climatological and Geophysics)
Author-email: Muhammad Dwi Reza <dwireza1002@gmail.com>
Project-URL: Homepage, https://github.com/Rex-Project-Organization/IndonesiaLatestEarthQuake
Classifier: Programming Language :: Python :: 3
Classifier: License :: OSI Approved :: GNU General Public License v3 (GPLv3)
Classifier: Operating System :: OS Independent
Classifier: Development Status :: 4 - Beta
Requires-Python: >=3.12
License-File: LICENSE
